<?xml version="1.0" encoding="UTF-8"?>
<actions>
<action>
	<icon>utilities-terminal</icon>
	<name>Open Terminal Here</name>
	<submenu></submenu>
	<unique-id>1737249781896228-1</unique-id>
	<command>alacritty  --working-directory %f
</command>
	<description>Example for a custom action</description>
	<range></range>
	<patterns>*</patterns>
	<startup-notify/>
	<directories/>
</action>
<action>
	<icon>vscode</icon>
	<name>Open with VS-code</name>
	<submenu></submenu>
	<unique-id>1737998733641970-1</unique-id>
	<command>code %f</command>
	<description></description>
	<range>*</range>
	<patterns>*</patterns>
	<directories/>
	<audio-files/>
	<image-files/>
	<other-files/>
	<text-files/>
	<video-files/>
</action>
<action>
	<icon>dialog-info</icon>
	<name> Media Info</name>
	<submenu></submenu>
	<unique-id>1745400325363209-1</unique-id>
	<command>/usr/local/bin/video-properties-mocha %f</command>
	<description></description>
	<range>*</range>
	<patterns>*</patterns>
	<image-files/>
	<video-files/>
</action>
</actions>
